interactive_visualization/__init__.py
interactive_visualization/animation_utils/__init__.py
interactive_visualization/animation_utils/animation.py
interactive_visualization/animation_utils/latex.py
interactive_visualization/animation_utils/matplotlib.py
interactive_visualization/graph_utils/__init__.py
interactive_visualization/graph_utils/fsa.py
interactive_visualization/graph_utils/graph.py
interactive_visualization-0.1.4.dist-info/LICENSE
interactive_visualization-0.1.4.dist-info/METADATA
interactive_visualization-0.1.4.dist-info/WHEEL
interactive_visualization-0.1.4.dist-info/top_level.txt
interactive_visualization-0.1.4.dist-info/RECORD
