Metadata-Version: 2.1
Name: interactive-visualization
Version: 0.1.4
Summary: Package provides a simple widget-based framework for interactive visualization of algorithms
Home-page: https://github.com/Malkovsky/interactive-visualization
Author: Nikolay Malkovsky
Author-email: malkovskynv@gmail.com
License: UNKNOWN
Project-URL: Bug Tracker, https://github.com/Malkovsky/interactive-visualization/issues
Platform: UNKNOWN
Classifier: Development Status :: 4 - Beta
Classifier: Topic :: Scientific/Engineering :: Visualization
Classifier: Programming Language :: Python :: 3
Classifier: License :: OSI Approved :: MIT License
Classifier: Operating System :: OS Independent
Requires-Python: >=3.7
License-File: LICENSE
Requires-Dist: graphviz
Requires-Dist: matplotlib
